jin_spider_tool/__init__.py
jin_spider_tool/flask_tool.py
jin_spider_tool/tool_main.py
jin_spider_tool-2.2.0.dist-info/LICENSE
jin_spider_tool-2.2.0.dist-info/METADATA
jin_spider_tool-2.2.0.dist-info/WHEEL
jin_spider_tool-2.2.0.dist-info/top_level.txt
jin_spider_tool-2.2.0.dist-info/RECORD
