Metadata-Version: 2.1
Name: jin-spider-tool
Version: 2.2.0
Summary: zookeeper ephemeral register
Home-page: http://git.baijia.com/st-spider/zkclient.git
Author: jin
Author-email: 1101156471@qq.com
License: UNKNOWN
Platform: UNKNOWN
Classifier: Programming Language :: Python :: 3
Classifier: License :: OSI Approved :: MIT License
Classifier: Operating System :: OS Independent
Requires: kazoo
Requires-Python: >=3.5
License-File: LICENSE
Requires-Dist: flask
Requires-Dist: kazoo
